{"Capital Gain: 0-Sex: 1": 1355, "Sex: 1-Capital Gain: 0": 1355, "Capital Gain: 0-Marital Status: 2": 900, "Marital Status: 2-Capital Gain: 0": 900, "Capital Gain: 0-Relationship: 0": 783, "Relationship: 0-Capital Gain: 0": 783, "Capital Gain: 0-Age: 3": 404, "Age: 3-Capital Gain: 0": 404, "Capital Gain: 0-Hours Per Week: 4": 362, "Hours Per Week: 4-Capital Gain: 0": 362, "Capital Gain: 0-Occupation: 9": 277, "Occupation: 9-Capital Gain: 0": 277, "Capital Gain: 0-Occupation: 3": 264, "Occupation: 3-Capital Gain: 0": 264, "Capital Gain: 0-Age: 4": 234, "Age: 4-Capital Gain: 0": 234, "Capital Gain: 0-Age: 5": 149, "Age: 5-Capital Gain: 0": 149, "Capital Gain: 0-Hours Per Week: 6": 98, "Hours Per Week: 6-Capital Gain: 0": 98, "Capital Gain: 0-Education: 12": 98, "Education: 12-Capital Gain: 0": 98, "Capital Gain: 0-Relationship: 5": 93, "Relationship: 5-Capital Gain: 0": 93, "Capital Gain: 0-Workclass: 3": 60, "Workclass: 3-Capital Gain: 0": 60, "Capital Gain: 0-Hours Per Week: 5": 67, "Hours Per Week: 5-Capital Gain: 0": 67, "Capital Gain: 0-Education: 14": 32, "Education: 14-Capital Gain: 0": 32, "Capital Gain: 0-Hours Per Week: 7": 27, "Hours Per Week: 7-Capital Gain: 0": 27, "Capital Gain: 0-Education: 10": 19, "Education: 10-Capital Gain: 0": 19, "Capital Gain: 0-Capital Loss: 5": 12, "Capital Loss: 5-Capital Gain: 0": 12, "Capital Gain: 0-Hours Per Week: 8": 15, "Hours Per Week: 8-Capital Gain: 0": 15, "Sex: 1-Sex: 1": 2000, "Sex: 1-Marital Status: 2": 1786, "Marital Status: 2-Sex: 1": 1786, "Sex: 1-Relationship: 0": 2000, "Relationship: 0-Sex: 1": 2000, "Sex: 1-Age: 3": 1419, "Age: 3-Sex: 1": 1419, "Sex: 1-Hours Per Week: 4": 1614, "Hours Per Week: 4-Sex: 1": 1614, "Sex: 1-Occupation: 9": 1273, "Occupation: 9-Sex: 1": 1273, "Sex: 1-Occupation: 3": 1421, "Occupation: 3-Sex: 1": 1421, "Sex: 1-Age: 4": 1419, "Age: 4-Sex: 1": 1419, "Sex: 1-Age: 5": 1455, "Age: 5-Sex: 1": 1455, "Sex: 1-Hours Per Week: 6": 1478, "Hours Per Week: 6-Sex: 1": 1478, "Sex: 1-Education: 12": 1118, "Education: 12-Sex: 1": 1118, "Sex: 1-Relationship: 5": 1, "Relationship: 5-Sex: 1": 1, "Sex: 1-Workclass: 3": 948, "Workclass: 3-Sex: 1": 948, "Sex: 1-Hours Per Week: 5": 838, "Hours Per Week: 5-Sex: 1": 838, "Sex: 1-Education: 14": 455, "Education: 14-Sex: 1": 455, "Sex: 1-Hours Per Week: 7": 358, "Hours Per Week: 7-Sex: 1": 358, "Sex: 1-Education: 10": 294, "Education: 10-Sex: 1": 294, "Sex: 1-Capital Loss: 5": 142, "Capital Loss: 5-Sex: 1": 142, "Sex: 1-Hours Per Week: 8": 16, "Hours Per Week: 8-Sex: 1": 16, "Marital Status: 2-Marital Status: 2": 2000, "Marital Status: 2-Relationship: 0": 2000, "Relationship: 0-Marital Status: 2": 2000, "Marital Status: 2-Age: 3": 1161, "Age: 3-Marital Status: 2": 1161, "Marital Status: 2-Hours Per Week: 4": 1174, "Hours Per Week: 4-Marital Status: 2": 1174, "Marital Status: 2-Occupation: 9": 1012, "Occupation: 9-Marital Status: 2": 1012, "Marital Status: 2-Occupation: 3": 1204, "Occupation: 3-Marital Status: 2": 1204, "Marital Status: 2-Age: 4": 1279, "Age: 4-Marital Status: 2": 1279, "Marital Status: 2-Age: 5": 1275, "Age: 5-Marital Status: 2": 1275, "Marital Status: 2-Hours Per Week: 6": 1129, "Hours Per Week: 6-Marital Status: 2": 1129, "Marital Status: 2-Education: 12": 942, "Education: 12-Marital Status: 2": 942, "Marital Status: 2-Relationship: 5": 1396, "Relationship: 5-Marital Status: 2": 1396, "Marital Status: 2-Workclass: 3": 802, "Workclass: 3-Marital Status: 2": 802, "Marital Status: 2-Hours Per Week: 5": 623, "Hours Per Week: 5-Marital Status: 2": 623, "Marital Status: 2-Education: 14": 386, "Education: 14-Marital Status: 2": 386, "Marital Status: 2-Hours Per Week: 7": 265, "Hours Per Week: 7-Marital Status: 2": 265, "Marital Status: 2-Education: 10": 258, "Education: 10-Marital Status: 2": 258, "Marital Status: 2-Capital Loss: 5": 100, "Capital Loss: 5-Marital Status: 2": 100, "Marital Status: 2-Hours Per Week: 8": 15, "Hours Per Week: 8-Marital Status: 2": 15, "Relationship: 0-Relationship: 0": 2000, "Relationship: 0-Age: 3": 1026, "Age: 3-Relationship: 0": 1026, "Relationship: 0-Hours Per Week: 4": 1129, "Hours Per Week: 4-Relationship: 0": 1129, "Relationship: 0-Occupation: 9": 886, "Occupation: 9-Relationship: 0": 886, "Relationship: 0-Occupation: 3": 1043, "Occupation: 3-Relationship: 0": 1043, "Relationship: 0-Age: 4": 1145, "Age: 4-Relationship: 0": 1145, "Relationship: 0-Age: 5": 1177, "Age: 5-Relationship: 0": 1177, "Relationship: 0-Hours Per Week: 6": 1090, "Hours Per Week: 6-Relationship: 0": 1090, "Relationship: 0-Education: 12": 831, "Education: 12-Relationship: 0": 831, "Relationship: 0-Relationship: 5": 0, "Relationship: 5-Relationship: 0": 0, "Relationship: 0-Workclass: 3": 756, "Workclass: 3-Relationship: 0": 756, "Relationship: 0-Hours Per Week: 5": 593, "Hours Per Week: 5-Relationship: 0": 593, "Relationship: 0-Education: 14": 360, "Education: 14-Relationship: 0": 360, "Relationship: 0-Hours Per Week: 7": 252, "Hours Per Week: 7-Relationship: 0": 252, "Relationship: 0-Education: 10": 239, "Education: 10-Relationship: 0": 239, "Relationship: 0-Capital Loss: 5": 88, "Capital Loss: 5-Relationship: 0": 88, "Relationship: 0-Hours Per Week: 8": 17, "Hours Per Week: 8-Relationship: 0": 17, "Age: 3-Age: 3": 2000, "Age: 3-Hours Per Week: 4": 471, "Hours Per Week: 4-Age: 3": 471, "Age: 3-Occupation: 9": 474, "Occupation: 9-Age: 3": 474, "Age: 3-Occupation: 3": 488, "Occupation: 3-Age: 3": 488, "Age: 3-Age: 4": 0, "Age: 4-Age: 3": 0, "Age: 3-Age: 5": 0, "Age: 5-Age: 3": 0, "Age: 3-Hours Per Week: 6": 427, "Hours Per Week: 6-Age: 3": 427, "Age: 3-Education: 12": 508, "Education: 12-Age: 3": 508, "Age: 3-Relationship: 5": 352, "Relationship: 5-Age: 3": 352, "Age: 3-Workclass: 3": 267, "Workclass: 3-Age: 3": 267, "Age: 3-Hours Per Week: 5": 245, "Hours Per Week: 5-Age: 3": 245, "Age: 3-Education: 14": 173, "Education: 14-Age: 3": 173, "Age: 3-Hours Per Week: 7": 100, "Hours Per Week: 7-Age: 3": 100, "Age: 3-Education: 10": 94, "Education: 10-Age: 3": 94, "Age: 3-Capital Loss: 5": 50, "Capital Loss: 5-Age: 3": 50, "Age: 3-Hours Per Week: 8": 10, "Hours Per Week: 8-Age: 3": 10, "Hours Per Week: 4-Hours Per Week: 4": 2000, "Hours Per Week: 4-Occupation: 9": 490, "Occupation: 9-Hours Per Week: 4": 490, "Hours Per Week: 4-Occupation: 3": 596, "Occupation: 3-Hours Per Week: 4": 596, "Hours Per Week: 4-Age: 4": 462, "Age: 4-Hours Per Week: 4": 462, "Hours Per Week: 4-Age: 5": 401, "Age: 5-Hours Per Week: 4": 401, "Hours Per Week: 4-Hours Per Week: 6": 0, "Hours Per Week: 6-Hours Per Week: 4": 0, "Hours Per Week: 4-Education: 12": 460, "Education: 12-Hours Per Week: 4": 460, "Hours Per Week: 4-Relationship: 5": 190, "Relationship: 5-Hours Per Week: 4": 190, "Hours Per Week: 4-Workclass: 3": 318, "Workclass: 3-Hours Per Week: 4": 318, "Hours Per Week: 4-Hours Per Week: 5": 0, "Hours Per Week: 5-Hours Per Week: 4": 0, "Hours Per Week: 4-Education: 14": 161, "Education: 14-Hours Per Week: 4": 161, "Hours Per Week: 4-Hours Per Week: 7": 0, "Hours Per Week: 7-Hours Per Week: 4": 0, "Hours Per Week: 4-Education: 10": 108, "Education: 10-Hours Per Week: 4": 108, "Hours Per Week: 4-Capital Loss: 5": 46, "Capital Loss: 5-Hours Per Week: 4": 46, "Hours Per Week: 4-Hours Per Week: 8": 0, "Hours Per Week: 8-Hours Per Week: 4": 0, "Occupation: 9-Occupation: 9": 2000, "Occupation: 9-Occupation: 3": 0, "Occupation: 3-Occupation: 9": 0, "Occupation: 9-Age: 4": 334, "Age: 4-Occupation: 9": 334, "Occupation: 9-Age: 5": 275, "Age: 5-Occupation: 9": 275, "Occupation: 9-Hours Per Week: 6": 306, "Hours Per Week: 6-Occupation: 9": 306, "Occupation: 9-Education: 12": 819, "Education: 12-Occupation: 9": 819, "Occupation: 9-Relationship: 5": 303, "Relationship: 5-Occupation: 9": 303, "Occupation: 9-Workclass: 3": 157, "Workclass: 3-Occupation: 9": 157, "Occupation: 9-Hours Per Week: 5": 154, "Hours Per Week: 5-Occupation: 9": 154, "Occupation: 9-Education: 14": 443, "Education: 14-Occupation: 9": 443, "Occupation: 9-Hours Per Week: 7": 67, "Hours Per Week: 7-Occupation: 9": 67, "Occupation: 9-Education: 10": 302, "Education: 10-Occupation: 9": 302, "Occupation: 9-Capital Loss: 5": 37, "Capital Loss: 5-Occupation: 9": 37, "Occupation: 9-Hours Per Week: 8": 13, "Hours Per Week: 8-Occupation: 9": 13, "Occupation: 3-Occupation: 3": 2000, "Occupation: 3-Age: 4": 356, "Age: 4-Occupation: 3": 356, "Occupation: 3-Age: 5": 321, "Age: 5-Occupation: 3": 321, "Occupation: 3-Hours Per Week: 6": 378, "Hours Per Week: 6-Occupation: 3": 378, "Occupation: 3-Education: 12": 491, "Education: 12-Occupation: 3": 491, "Occupation: 3-Relationship: 5": 236, "Relationship: 5-Occupation: 3": 236, "Occupation: 3-Workclass: 3": 385, "Workclass: 3-Occupation: 3": 385, "Occupation: 3-Hours Per Week: 5": 237, "Hours Per Week: 5-Occupation: 3": 237, "Occupation: 3-Education: 14": 48, "Education: 14-Occupation: 3": 48, "Occupation: 3-Hours Per Week: 7": 77, "Hours Per Week: 7-Occupation: 3": 77, "Occupation: 3-Education: 10": 54, "Education: 10-Occupation: 3": 54, "Occupation: 3-Capital Loss: 5": 50, "Capital Loss: 5-Occupation: 3": 50, "Occupation: 3-Hours Per Week: 8": 11, "Hours Per Week: 8-Occupation: 3": 11, "Age: 4-Age: 4": 2000, "Age: 4-Age: 5": 0, "Age: 5-Age: 4": 0, "Age: 4-Hours Per Week: 6": 285, "Hours Per Week: 6-Age: 4": 285, "Age: 4-Education: 12": 334, "Education: 12-Age: 4": 334, "Age: 4-Relationship: 5": 210, "Relationship: 5-Age: 4": 210, "Age: 4-Workclass: 3": 226, "Workclass: 3-Age: 4": 226, "Age: 4-Hours Per Week: 5": 150, "Hours Per Week: 5-Age: 4": 150, "Age: 4-Education: 14": 89, "Education: 14-Age: 4": 89, "Age: 4-Hours Per Week: 7": 63, "Hours Per Week: 7-Age: 4": 63, "Age: 4-Education: 10": 89, "Education: 10-Age: 4": 89, "Age: 4-Capital Loss: 5": 30, "Capital Loss: 5-Age: 4": 30, "Age: 4-Hours Per Week: 8": 16, "Hours Per Week: 8-Age: 4": 16, "Age: 5-Age: 5": 2000, "Age: 5-Hours Per Week: 6": 159, "Hours Per Week: 6-Age: 5": 159, "Age: 5-Education: 12": 179, "Education: 12-Age: 5": 179, "Age: 5-Relationship: 5": 108, "Relationship: 5-Age: 5": 108, "Age: 5-Workclass: 3": 139, "Workclass: 3-Age: 5": 139, "Age: 5-Hours Per Week: 5": 80, "Hours Per Week: 5-Age: 5": 80, "Age: 5-Education: 14": 54, "Education: 14-Age: 5": 54, "Age: 5-Hours Per Week: 7": 32, "Hours Per Week: 7-Age: 5": 32, "Age: 5-Education: 10": 51, "Education: 10-Age: 5": 51, "Age: 5-Capital Loss: 5": 22, "Capital Loss: 5-Age: 5": 22, "Age: 5-Hours Per Week: 8": 11, "Hours Per Week: 8-Age: 5": 11, "Hours Per Week: 6-Hours Per Week: 6": 1721, "Hours Per Week: 6-Education: 12": 157, "Education: 12-Hours Per Week: 6": 157, "Hours Per Week: 6-Relationship: 5": 34, "Relationship: 5-Hours Per Week: 6": 34, "Hours Per Week: 6-Workclass: 3": 201, "Workclass: 3-Hours Per Week: 6": 201, "Hours Per Week: 6-Hours Per Week: 5": 0, "Hours Per Week: 5-Hours Per Week: 6": 0, "Hours Per Week: 6-Education: 14": 86, "Education: 14-Hours Per Week: 6": 86, "Hours Per Week: 6-Hours Per Week: 7": 0, "Hours Per Week: 7-Hours Per Week: 6": 0, "Hours Per Week: 6-Education: 10": 64, "Education: 10-Hours Per Week: 6": 64, "Hours Per Week: 6-Capital Loss: 5": 22, "Capital Loss: 5-Hours Per Week: 6": 22, "Hours Per Week: 6-Hours Per Week: 8": 0, "Hours Per Week: 8-Hours Per Week: 6": 0, "Education: 12-Education: 12": 1627, "Education: 12-Relationship: 5": 106, "Relationship: 5-Education: 12": 106, "Education: 12-Workclass: 3": 77, "Workclass: 3-Education: 12": 77, "Education: 12-Hours Per Week: 5": 74, "Hours Per Week: 5-Education: 12": 74, "Education: 12-Education: 14": 0, "Education: 14-Education: 12": 0, "Education: 12-Hours Per Week: 7": 32, "Hours Per Week: 7-Education: 12": 32, "Education: 12-Education: 10": 0, "Education: 10-Education: 12": 0, "Education: 12-Capital Loss: 5": 18, "Capital Loss: 5-Education: 12": 18, "Education: 12-Hours Per Week: 8": 12, "Hours Per Week: 8-Education: 12": 12, "Relationship: 5-Relationship: 5": 1406, "Relationship: 5-Workclass: 3": 42, "Workclass: 3-Relationship: 5": 42, "Relationship: 5-Hours Per Week: 5": 27, "Hours Per Week: 5-Relationship: 5": 27, "Relationship: 5-Education: 14": 25, "Education: 14-Relationship: 5": 25, "Relationship: 5-Hours Per Week: 7": 10, "Hours Per Week: 7-Relationship: 5": 10, "Relationship: 5-Education: 10": 18, "Education: 10-Relationship: 5": 18, "Relationship: 5-Capital Loss: 5": 10, "Capital Loss: 5-Relationship: 5": 10, "Relationship: 5-Hours Per Week: 8": 2, "Hours Per Week: 8-Relationship: 5": 2, "Workclass: 3-Workclass: 3": 1074, "Workclass: 3-Hours Per Week: 5": 63, "Hours Per Week: 5-Workclass: 3": 63, "Workclass: 3-Education: 14": 79, "Education: 14-Workclass: 3": 79, "Workclass: 3-Hours Per Week: 7": 51, "Hours Per Week: 7-Workclass: 3": 51, "Workclass: 3-Education: 10": 33, "Education: 10-Workclass: 3": 33, "Workclass: 3-Capital Loss: 5": 30, "Capital Loss: 5-Workclass: 3": 30, "Workclass: 3-Hours Per Week: 8": 22, "Hours Per Week: 8-Workclass: 3": 22, "Hours Per Week: 5-Hours Per Week: 5": 1018, "Hours Per Week: 5-Education: 14": 40, "Education: 14-Hours Per Week: 5": 40, "Hours Per Week: 5-Hours Per Week: 7": 0, "Hours Per Week: 7-Hours Per Week: 5": 0, "Hours Per Week: 5-Education: 10": 19, "Education: 10-Hours Per Week: 5": 19, "Hours Per Week: 5-Capital Loss: 5": 12, "Capital Loss: 5-Hours Per Week: 5": 12, "Hours Per Week: 5-Hours Per Week: 8": 0, "Hours Per Week: 8-Hours Per Week: 5": 0, "Education: 14-Education: 14": 542, "Education: 14-Hours Per Week: 7": 19, "Hours Per Week: 7-Education: 14": 19, "Education: 14-Education: 10": 0, "Education: 10-Education: 14": 0, "Education: 14-Capital Loss: 5": 19, "Capital Loss: 5-Education: 14": 19, "Education: 14-Hours Per Week: 8": 13, "Hours Per Week: 8-Education: 14": 13, "Hours Per Week: 7-Hours Per Week: 7": 421, "Hours Per Week: 7-Education: 10": 14, "Education: 10-Hours Per Week: 7": 14, "Hours Per Week: 7-Capital Loss: 5": 6, "Capital Loss: 5-Hours Per Week: 7": 6, "Hours Per Week: 7-Hours Per Week: 8": 0, "Hours Per Week: 8-Hours Per Week: 7": 0, "Education: 10-Education: 10": 375, "Education: 10-Capital Loss: 5": 8, "Capital Loss: 5-Education: 10": 8, "Education: 10-Hours Per Week: 8": 5, "Hours Per Week: 8-Education: 10": 5, "Capital Loss: 5-Capital Loss: 5": 189, "Capital Loss: 5-Hours Per Week: 8": 4, "Hours Per Week: 8-Capital Loss: 5": 4}